badness_utils.py
data_io.py
design_primers.py
iterative.py
main.py
optimization.py
prism_bio-1.0.4.dist-info/licenses/LICENSE
prism_bio-1.0.4.dist-info/METADATA
prism_bio-1.0.4.dist-info/WHEEL
prism_bio-1.0.4.dist-info/entry_points.txt
prism_bio-1.0.4.dist-info/top_level.txt
prism_bio-1.0.4.dist-info/RECORD
